{
  "players": [
    {
      "name": "김형철",
      "win": 33,
      "draw": 19,
      "lose": 28,
      "plays": 13,
      "pts": 118
    },
    {
      "name": "송효석",
      "win": 22,
      "draw": 6,
      "lose": 14,
      "plays": 7,
      "pts": 72
    },
    {
      "name": "박재범",
      "win": 28,
      "draw": 13,
      "lose": 33,
      "plays": 12,
      "pts": 97
    },
    {
      "name": "권위준",
      "win": 24,
      "draw": 11,
      "lose": 21,
      "plays": 9,
      "pts": 83
    },
    {
      "name": "신종은",
      "win": 0,
      "draw": 0,
      "lose": 0,
      "plays": 0,
      "pts": 0
    },
    {
      "name": "이정일",
      "win": 29,
      "draw": 21,
      "lose": 36,
      "plays": 14,
      "pts": 108
    },
    {
      "name": "조돈휘",
      "win": 11,
      "draw": 10,
      "lose": 9,
      "plays": 5,
      "pts": 43
    },
    {
      "name": "현종권",
      "win": 29,
      "draw": 21,
      "lose": 36,
      "plays": 14,
      "pts": 108
    },
    {
      "name": "곽영래",
      "win": 25,
      "draw": 15,
      "lose": 34,
      "plays": 12,
      "pts": 90
    },
    {
      "name": "정회화",
      "win": 22,
      "draw": 14,
      "lose": 32,
      "plays": 11,
      "pts": 80
    },
    {
      "name": "김상명",
      "win": 0,
      "draw": 0,
      "lose": 0,
      "plays": 0,
      "pts": 0
    },
    {
      "name": "신종윤",
      "win": 35,
      "draw": 16,
      "lose": 29,
      "plays": 13,
      "pts": 121
    },
    {
      "name": "황성진",
      "win": 3,
      "draw": 0,
      "lose": 3,
      "plays": 1,
      "pts": 9
    },
    {
      "name": "이병철",
      "win": 21,
      "draw": 12,
      "lose": 17,
      "plays": 8,
      "pts": 75
    },
    {
      "name": "강동균",
      "win": 12,
      "draw": 6,
      "lose": 12,
      "plays": 5,
      "pts": 42
    },
    {
      "name": "류희대",
      "win": 0,
      "draw": 0,
      "lose": 0,
      "plays": 0,
      "pts": 0
    },
    {
      "name": "여성진",
      "win": 0,
      "draw": 0,
      "lose": 0,
      "plays": 0,
      "pts": 0
    },
    {
      "name": "김영준",
      "win": 31,
      "draw": 15,
      "lose": 16,
      "plays": 10,
      "pts": 108
    },
    {
      "name": "장효준",
      "win": 29,
      "draw": 12,
      "lose": 19,
      "plays": 10,
      "pts": 99
    },
    {
      "name": "정기택",
      "win": 21,
      "draw": 9,
      "lose": 24,
      "plays": 9,
      "pts": 72
    },
    {
      "name": "김정민",
      "win": 13,
      "draw": 11,
      "lose": 24,
      "plays": 8,
      "pts": 50
    },
    {
      "name": "정현준",
      "win": 22,
      "draw": 5,
      "lose": 15,
      "plays": 7,
      "pts": 71
    },
    {
      "name": "김주환",
      "win": 25,
      "draw": 8,
      "lose": 21,
      "plays": 9,
      "pts": 83
    },
    {
      "name": "이지철",
      "win": 23,
      "draw": 10,
      "lose": 17,
      "plays": 8,
      "pts": 79
    },
    {
      "name": "김진호",
      "win": 38,
      "draw": 15,
      "lose": 31,
      "plays": 14,
      "pts": 129
    },
    {
      "name": "박진산",
      "win": 18,
      "draw": 12,
      "lose": 12,
      "plays": 7,
      "pts": 66
    },
    {
      "name": "임다훈",
      "win": 3,
      "draw": 5,
      "lose": 10,
      "plays": 3,
      "pts": 14
    },
    {
      "name": "강병준",
      "win": 21,
      "draw": 17,
      "lose": 28,
      "plays": 11,
      "pts": 80
    },
    {
      "name": "박찬용",
      "win": 26,
      "draw": 14,
      "lose": 22,
      "plays": 10,
      "pts": 92
    },
    {
      "name": "이종범",
      "win": 21,
      "draw": 16,
      "lose": 19,
      "plays": 9,
      "pts": 79
    },
    {
      "name": "박기환",
      "win": 24,
      "draw": 16,
      "lose": 20,
      "plays": 10,
      "pts": 88
    },
    {
      "name": "이주은",
      "win": 3,
      "draw": 4,
      "lose": 5,
      "plays": 2,
      "pts": 13
    },
    {
      "name": "권현택",
      "win": 2,
      "draw": 2,
      "lose": 2,
      "plays": 1,
      "pts": 8
    },
    {
      "name": "이성혁",
      "win": 8,
      "draw": 5,
      "lose": 11,
      "plays": 4,
      "pts": 29
    },
    {
      "name": "이상욱",
      "win": 1,
      "draw": 4,
      "lose": 1,
      "plays": 1,
      "pts": 7
    },
    {
      "name": "박준영",
      "win": 4,
      "draw": 2,
      "lose": 6,
      "plays": 2,
      "pts": 14
    },
    {
      "name": "윤한중",
      "win": 14,
      "draw": 13,
      "lose": 27,
      "plays": 9,
      "pts": 55
    },
    {
      "name": "전지민",
      "win": 5,
      "draw": 1,
      "lose": 6,
      "plays": 2,
      "pts": 16
    },
    {
      "name": "권순국",
      "win": 22,
      "draw": 18,
      "lose": 26,
      "plays": 11,
      "pts": 84
    },
    {
      "name": "조대인",
      "win": 11,
      "draw": 12,
      "lose": 7,
      "plays": 5,
      "pts": 45
    }
  ]
}